modelz/__init__.py
modelz/aioclient.py
modelz/args.py
modelz/client.py
modelz/cmd.py
modelz/env.py
modelz/serde.py
modelz/utils.py
modelz/__version__.py
aiomodelz-0.4.10.dist-info/entry_points.txt
aiomodelz-0.4.10.dist-info/WHEEL
aiomodelz-0.4.10.dist-info/METADATA
aiomodelz-0.4.10.dist-info/licenses/LICENSE.modelz-py
aiomodelz-0.4.10.dist-info/licenses/LICENSE
aiomodelz-0.4.10.dist-info/RECORD
