Metadata-Version: 2.1
Name: aiomodelz
Version: 0.4.10
Summary: machine learning models
License: Apache-2.0
Keywords: machine learning,deep learning
Author-email: Teddy Xinyuan Chen <45612704+tddschn@users.noreply.github.com>,TensorChord <modelz-support@tensorchord.ai>
Requires-Python: >=3.7
Classifier: Environment :: GPU
Classifier: Intended Audience :: Developers
Classifier: Topic :: Scientific/Engineering :: Artificial Intelligence
Requires-Dist: aiohttp>=3.8.4
Requires-Dist: msgpack>=1.0.4
Requires-Dist: rich>=12.6.0
Requires-Dist: typer[all]>=0.7.0
